jsphinx/__init__.py
jsphinx-0.0.1.dist-info/LICENSE
jsphinx-0.0.1.dist-info/METADATA
jsphinx-0.0.1.dist-info/WHEEL
jsphinx-0.0.1.dist-info/top_level.txt
jsphinx-0.0.1.dist-info/RECORD
