Metadata-Version: 2.1
Name: jsphinx
Version: 0.0.1
Summary: Java documentation for Python Sphinx.
Home-page: https://github.com/phuang1024/jsphinx
Author: Patrick Huang
Author-email: huangpatrick16777216@gmail.com
License: UNKNOWN
Platform: UNKNOWN
Classifier: Programming Language :: Python :: 3
Classifier: License :: OSI Approved :: GNU General Public License v2 or later (GPLv2+)
Classifier: Operating System :: OS Independent
Requires-Dist: sphinx
